{
    "errors": [
        "EXIT_CODE_8"
    ],
    "fails": [],
    "findings": [
        {
            "confidence": "High",
            "contract": "WaRoll",
            "filename": "output/0x22d2913a4bf16c8dcf1ee655f9b547ac55368f88.sol",
            "function": "setCroupier",
            "impact": "Informational",
            "line": 62,
            "line_end": 66,
            "message": "WaRoll.setCroupier (0x22d2913a4bf16c8dcf1ee655f9b547ac55368f88.sol#62-66) should be declared external\n",
            "name": "external-function"
        },
        {
            "confidence": "High",
            "contract": "WaRoll",
            "filename": "output/0x22d2913a4bf16c8dcf1ee655f9b547ac55368f88.sol",
            "function": "setSigner",
            "impact": "Informational",
            "line": 66,
            "line_end": 71,
            "message": "WaRoll.setSigner (0x22d2913a4bf16c8dcf1ee655f9b547ac55368f88.sol#66-71) should be declared external\n",
            "name": "external-function"
        },
        {
            "confidence": "High",
            "contract": "WaRoll",
            "filename": "output/0x22d2913a4bf16c8dcf1ee655f9b547ac55368f88.sol",
            "function": "kill",
            "impact": "Informational",
            "line": 72,
            "line_end": 74,
            "message": "WaRoll.kill (0x22d2913a4bf16c8dcf1ee655f9b547ac55368f88.sol#72-74) should be declared external\n",
            "name": "external-function"
        },
        {
            "confidence": "High",
            "contract": "WaRoll",
            "filename": "output/0x22d2913a4bf16c8dcf1ee655f9b547ac55368f88.sol",
            "function": "doRollBet",
            "impact": "Informational",
            "line": 74,
            "line_end": 88,
            "message": "WaRoll.doRollBet (0x22d2913a4bf16c8dcf1ee655f9b547ac55368f88.sol#74-88) should be declared external\n",
            "name": "external-function"
        },
        {
            "confidence": "High",
            "contract": "WaRoll",
            "filename": "output/0x22d2913a4bf16c8dcf1ee655f9b547ac55368f88.sol",
            "function": "doRouletteBet",
            "impact": "Informational",
            "line": 88,
            "line_end": 102,
            "message": "WaRoll.doRouletteBet (0x22d2913a4bf16c8dcf1ee655f9b547ac55368f88.sol#88-102) should be declared external\n",
            "name": "external-function"
        },
        {
            "confidence": "High",
            "contract": "WaRoll",
            "filename": "output/0x22d2913a4bf16c8dcf1ee655f9b547ac55368f88.sol",
            "function": "doResult",
            "impact": "Informational",
            "line": 111,
            "line_end": 123,
            "message": "WaRoll.doResult (0x22d2913a4bf16c8dcf1ee655f9b547ac55368f88.sol#111-123) should be declared external\n",
            "name": "external-function"
        },
        {
            "confidence": "High",
            "contract": "WaRoll",
            "filename": "output/0x22d2913a4bf16c8dcf1ee655f9b547ac55368f88.sol",
            "function": "fallback",
            "impact": "Informational",
            "message": "WaRoll.fallback (0x22d2913a4bf16c8dcf1ee655f9b547ac55368f88.sol) should be declared external\n",
            "name": "external-function"
        },
        {
            "confidence": "High",
            "contract": "WaRoll",
            "filename": "output/0x22d2913a4bf16c8dcf1ee655f9b547ac55368f88.sol",
            "function": "withdraw",
            "impact": "Informational",
            "message": "WaRoll.withdraw (0x22d2913a4bf16c8dcf1ee655f9b547ac55368f88.sol) should be declared external\n",
            "name": "external-function"
        }
    ],
    "infos": [],
    "parser": {
        "id": "slither",
        "mode": "solidity",
        "version": "2022/11/14"
    }
}
